okrand/.DS_Store
okrand/__init__.py
okrand/apps.py
okrand/iommi_admin.py
okrand/views.py
okrand/_vendored/polib.py
okrand/management/.DS_Store
okrand/management/__init__.py
okrand/management/commands/.DS_Store
okrand/management/commands/__init__.py
okrand/management/commands/i18n.py
okrand-1.5.1.dist-info/AUTHORS.rst
okrand-1.5.1.dist-info/LICENSE
okrand-1.5.1.dist-info/METADATA
okrand-1.5.1.dist-info/WHEEL
okrand-1.5.1.dist-info/top_level.txt
okrand-1.5.1.dist-info/RECORD
