Metadata-Version: 2.1
Name: okrand
Version: 1.5.1
Summary: Okrand is an internationalization/translation tool for Django
Home-page: https://github.com/boxed/okrand
Author: Anders Hovmöller
Author-email: boxed@killingar.net
License: BSD
Keywords: okrand
Classifier: Development Status :: 4 - Beta
Classifier: Intended Audience :: Developers
Classifier: License :: OSI Approved :: BSD License
Classifier: Natural Language :: English
Classifier: Programming Language :: Python :: 3
License-File: LICENSE
License-File: AUTHORS.rst
Requires-Dist: Django (>=3.2)
Requires-Dist: gitignorefile
